screen_capture_agent/capture_agent.py
capture_bot-0.1.0.dist-info/METADATA
capture_bot-0.1.0.dist-info/WHEEL
capture_bot-0.1.0.dist-info/top_level.txt
capture_bot-0.1.0.dist-info/RECORD
