Metadata-Version: 2.2
Name: capture_bot
Version: 0.1.0
Summary: A Python project for screen capture
Author: Your Name
Author-email: Your Name <your.email@example.com>
Requires-Dist: pyautogui
Requires-Dist: pynput
Requires-Dist: Pillow>=9.2.0
Dynamic: author
